pg_materialize/__init__.py
pg_materialize/pg_materialize.py
pg_materialize-0.4.1.dist-info/DESCRIPTION.rst
pg_materialize-0.4.1.dist-info/METADATA
pg_materialize-0.4.1.dist-info/RECORD
pg_materialize-0.4.1.dist-info/WHEEL
pg_materialize-0.4.1.dist-info/entry_points.txt
pg_materialize-0.4.1.dist-info/metadata.json
pg_materialize-0.4.1.dist-info/pbr.json
pg_materialize-0.4.1.dist-info/top_level.txt
