Metadata-Version: 2.0
Name: pg-materialize
Version: 0.4.1
Summary: Postgres Materialized View Dependency Manager
Home-page: https://github.com/aanari/pg-materialize
Author: Ali Anari
Author-email: ali@anari.io
License: MIT License
Keywords: pg
Requires-Dist: Pygments
Requires-Dist: click (<7.0,>=5.0)
Requires-Dist: psqlparse (==1.0rc5)
Requires-Dist: six
Requires-Dist: toolz
Requires-Dist: toposort
